./.env.sample
./.gitignore
./CHANGELOG.md
./LICENSE
./PKG-INFO
./PYPI_SETUP.md
./README.md
./browser_agent.py
./pyproject.toml
./server.py
./task_manager.py
./test_server.py
./uv.lock
./.claude/commands/question.md
./.claude/commands/quick-plan.md
./.claude/output-styles/bullet-points.md
./.claude/output-styles/genui.md
./.claude/output-styles/html-structured.md
./.claude/output-styles/markdown-focused.md
./.claude/output-styles/observable-tools-diffs-tts.md
./.claude/output-styles/observable-tools-diffs.md
./.claude/output-styles/table-based.md
./.claude/output-styles/tts-summary-base.md
./.claude/output-styles/tts-summary.md
./.claude/output-styles/ultra-concise.md
./.claude/output-styles/yaml-structured.md
./.claude/status_lines/status_line.py
./.claude/status_lines/status_line_v2.py
./.claude/status_lines/status_line_v3.py
./.claude/status_lines/status_line_v4.py
./.github/workflows/publish.yml
./.github/workflows/test.yml
computer_use_mcp-1.0.0.dist-info/METADATA
computer_use_mcp-1.0.0.dist-info/WHEEL
computer_use_mcp-1.0.0.dist-info/entry_points.txt
computer_use_mcp-1.0.0.dist-info/licenses/LICENSE
computer_use_mcp-1.0.0.dist-info/RECORD
