Metadata-Version: 2.4
Name: computer-use-mcp
Version: 1.0.0
Summary: Production-ready MCP server providing AI-powered web browsing automation using Gemini 2.5 Computer Use API
Project-URL: Homepage, https://github.com/vincenthopf/computer-use-mcp
Project-URL: Documentation, https://github.com/vincenthopf/computer-use-mcp#readme
Project-URL: Repository, https://github.com/vincenthopf/computer-use-mcp
Project-URL: Issues, https://github.com/vincenthopf/computer-use-mcp/issues
Project-URL: Changelog, https://github.com/vincenthopf/computer-use-mcp/blob/main/CHANGELOG.md
Author-email: Vincent Hopf <vincent@example.com>
License: MIT
License-File: LICENSE
Keywords: ai-agents,browser-automation,claude-desktop,computer-use,gemini,mcp,playwright,web-scraping
Classifier: Development Status :: 4 - Beta
Classifier: Intended Audience :: Developers
Classifier: License :: OSI Approved :: MIT License
Classifier: Programming Language :: Python :: 3.10
Classifier: Programming Language :: Python :: 3.11
Classifier: Programming Language :: Python :: 3.12
Classifier: Programming Language :: Python :: 3.13
Classifier: Topic :: Internet :: WWW/HTTP :: Browsers
Classifier: Topic :: Scientific/Engineering :: Artificial Intelligence
Classifier: Topic :: Software Development :: Libraries :: Python Modules
Requires-Python: >=3.10
Requires-Dist: anyio>=4.0.0
Requires-Dist: google-genai>=1.0.0
Requires-Dist: mcp[cli]>=1.0.0
Requires-Dist: playwright>=1.40.0
Requires-Dist: python-dotenv>=1.0.0
Provides-Extra: dev
Requires-Dist: pytest-asyncio>=0.21.0; extra == 'dev'
Requires-Dist: pytest>=7.0.0; extra == 'dev'
